avtcam/__init__.py
avtcam/avt_camera.py
avtcam/hi_avt.py
avtcam-0.2.0.dist-info/DESCRIPTION.rst
avtcam-0.2.0.dist-info/METADATA
avtcam-0.2.0.dist-info/RECORD
avtcam-0.2.0.dist-info/WHEEL
avtcam-0.2.0.dist-info/metadata.json
avtcam-0.2.0.dist-info/top_level.txt
