Metadata-Version: 2.0
Name: avtcam
Version: 0.2.0
Summary: An easy to use Allied Vision camera interface for NVIDIA Jetson and other third-party embedded platforms
Home-page: https://github.com/SunnyAVT/avtcam
Author: SunnyAVT
Author-email: lxftm@hotmail.com
License: UNKNOWN
Keywords: python,python3,opencv,cv,machine vision,computer vision,image recognition,vimba,allied vision
Platform: UNKNOWN
Requires-Dist: numpy
Requires-Dist: pymba
Requires-Dist: traitlets
